bbcloud_python_sdk/Exceptions.py
bbcloud_python_sdk/__init__.py
bbcloud_python_sdk/test.py
bbcloud_python_sdk/Api/Exceptions.py
bbcloud_python_sdk/Api/__init__.py
bbcloud_python_sdk/Api/Models/Artifacts.py
bbcloud_python_sdk/Api/Models/AutoTestOrders.py
bbcloud_python_sdk/Api/Models/AutoTestOrdersItems.py
bbcloud_python_sdk/Api/Models/Bags.py
bbcloud_python_sdk/Api/Models/Cocos2dCompileOrder.py
bbcloud_python_sdk/Api/Models/Cocos2dCompileOrdersItem.py
bbcloud_python_sdk/Api/Models/Http.py
bbcloud_python_sdk/Api/Models/Model.py
bbcloud_python_sdk/Api/Models/PhoneCabinets.py
bbcloud_python_sdk/Api/Models/Phones.py
bbcloud_python_sdk/Api/Models/Query.py
bbcloud_python_sdk/Api/Models/SDK.py
bbcloud_python_sdk/Api/Models/SubPacketTasks.py
bbcloud_python_sdk/Api/Models/Unity3dCompileOrder.py
bbcloud_python_sdk/Api/Models/User.py
bbcloud_python_sdk/Api/Models/__init__.py
bbcloud_python_sdk/FileCache/ObsFileCache.py
bbcloud_python_sdk/FileCache/OssFileCache.py
bbcloud_python_sdk/FileCache/SynologyFileCache.py
bbcloud_python_sdk/FileCache/__init__.py
bbcloud_python_sdk-0.0.52.dist-info/LICENSE
bbcloud_python_sdk-0.0.52.dist-info/METADATA
bbcloud_python_sdk-0.0.52.dist-info/WHEEL
bbcloud_python_sdk-0.0.52.dist-info/top_level.txt
bbcloud_python_sdk-0.0.52.dist-info/RECORD
