Metadata-Version: 2.1
Name: bbcloud-python-sdk
Version: 0.0.52
Summary: bbcloud python sdk
Home-page: https://github.com/bbcloudGroup/bbcloud_python_sdk
Author: BBCloud
Author-email: zealiemai@gmail.com
License: UNKNOWN
Platform: UNKNOWN
Classifier: Programming Language :: Python :: 3
Classifier: License :: OSI Approved :: MIT License
Classifier: Operating System :: OS Independent
License-File: LICENSE
Requires-Dist: oss2 (==2.14.0)
Requires-Dist: synology-api (==0.1.3.3)
Requires-Dist: esdk-obs-python (==3.21.4)
Requires-Dist: requests (==2.25.1)
